setup.cfg
setup.py
minipgm/__init__.py
minipgm/distributions.py
minipgm/models.py
minipgm/samplers.py
minipgm/variables.py
minipgm.egg-info/PKG-INFO
minipgm.egg-info/SOURCES.txt
minipgm.egg-info/dependency_links.txt
minipgm.egg-info/top_level.txt