Metadata-Version: 1.1
Name: minipgm
Version: 0.1.0
Summary: A minimalistic probabilistic programming framework.
Home-page: UNKNOWN
Author: Arnaud Rachez
Author-email: arnaud.rachez@gmail.com
License: UNKNOWN
Platform: UNKNOWN
Requires: numpy
Requires: scipy
